{
  "generated_at": "2026-07-17T01:45:51+00:00",
  "note": "Auto-generated from public RSS feeds. Confidence 'Unverified' means no human review yet. Coordinates are region centroids.",
  "events": [
    {
      "id": "RSS-0697061e8f",
      "date": "2026-07-17",
      "region": "Global",
      "location": "Global",
      "lat": 10.0,
      "lon": 0.0,
      "category": "Geopolitical",
      "event_type": "Public news report",
      "source_name": "Al Jazeera",
      "source_url": "https://www.aljazeera.com/video/newsfeed/2026/7/17/falling-debris-from-intercepted-iranian-strikes-sparks-fires-in-kuwait?traffic_source=rss",
      "summary": "Falling debris from intercepted Iranian strikes sparks fires in Kuwait",
      "why_it_matters": "Auto-ingested from public RSS; pending analyst annotation.",
      "confidence": "Unverified",
      "risk_score": 6,
      "tags": [
        "rss",
        "auto-ingested"
      ]
    },
    {
      "id": "RSS-ae69a0ea75",
      "date": "2026-07-17",
      "region": "Global",
      "location": "Global",
      "lat": 10.0,
      "lon": 0.0,
      "category": "Geopolitical",
      "event_type": "Public news report",
      "source_name": "Al Jazeera",
      "source_url": "https://www.aljazeera.com/sports/2026/7/17/brazilian-football-legend-peles-world-cup-shirt-sells-for-4-9-million?traffic_source=rss",
      "summary": "Brazilian football legend Pele\u2019s World Cup shirt sells for $4.9m",
      "why_it_matters": "Auto-ingested from public RSS; pending analyst annotation.",
      "confidence": "Unverified",
      "risk_score": 3,
      "tags": [
        "rss",
        "auto-ingested"
      ]
    },
    {
      "id": "RSS-90595a71c2",
      "date": "2026-07-16",
      "region": "Middle East",
      "location": "Middle East",
      "lat": 29.0,
      "lon": 45.0,
      "category": "Geopolitical",
      "event_type": "Public news report",
      "source_name": "Al Jazeera",
      "source_url": "https://www.aljazeera.com/news/2026/7/16/us-mounts-sixth-straight-night-of-attacks-as-iran-warns-of-wider-war?traffic_source=rss",
      "summary": "Iran says seven killed in latest US strikes, warns war \u2018will spread\u2019",
      "why_it_matters": "Auto-ingested from public RSS; pending analyst annotation.",
      "confidence": "Unverified",
      "risk_score": 9,
      "tags": [
        "rss",
        "auto-ingested"
      ]
    },
    {
      "id": "RSS-d9c7ae522a",
      "date": "2026-07-16",
      "region": "Middle East",
      "location": "Middle East",
      "lat": 29.0,
      "lon": 45.0,
      "category": "Geopolitical",
      "event_type": "Public news report",
      "source_name": "BBC World",
      "source_url": "https://www.bbc.co.uk/news/articles/c151gdjwd10o?at_medium=RSS&at_campaign=rss",
      "summary": "Blasts reported in Iran as US launches new wave of strikes",
      "why_it_matters": "Auto-ingested from public RSS; pending analyst annotation.",
      "confidence": "Unverified",
      "risk_score": 6,
      "tags": [
        "rss",
        "auto-ingested"
      ]
    },
    {
      "id": "RSS-f0d6ee3d94",
      "date": "2026-07-16",
      "region": "Global",
      "location": "Global",
      "lat": 10.0,
      "lon": 0.0,
      "category": "Geopolitical",
      "event_type": "Public news report",
      "source_name": "BBC World",
      "source_url": "https://www.bbc.co.uk/news/articles/c36dnz1zez5o?at_medium=RSS&at_campaign=rss",
      "summary": "Italian officials handed jail terms for Genoa bridge disaster that killed 43",
      "why_it_matters": "Auto-ingested from public RSS; pending analyst annotation.",
      "confidence": "Unverified",
      "risk_score": 6,
      "tags": [
        "rss",
        "auto-ingested"
      ]
    },
    {
      "id": "RSS-68705eab5a",
      "date": "2026-07-16",
      "region": "Global",
      "location": "Global",
      "lat": 10.0,
      "lon": 0.0,
      "category": "Military",
      "event_type": "Public news report",
      "source_name": "BBC World",
      "source_url": "https://www.bbc.co.uk/news/articles/c86262j7j75o?at_medium=RSS&at_campaign=rss",
      "summary": "As heatwaves strike, Europeans turn to prized Chinese air-conditioner",
      "why_it_matters": "Auto-ingested from public RSS; pending analyst annotation.",
      "confidence": "Unverified",
      "risk_score": 6,
      "tags": [
        "rss",
        "auto-ingested"
      ]
    },
    {
      "id": "RSS-ba49a28d51",
      "date": "2026-07-16",
      "region": "Global",
      "location": "Global",
      "lat": 10.0,
      "lon": 0.0,
      "category": "Military",
      "event_type": "Public news report",
      "source_name": "BBC World",
      "source_url": "https://www.bbc.co.uk/news/articles/cn4d4eq9n8do?at_medium=RSS&at_campaign=rss",
      "summary": "One man's hunger strike changed India's map. Can it still change politics?",
      "why_it_matters": "Auto-ingested from public RSS; pending analyst annotation.",
      "confidence": "Unverified",
      "risk_score": 6,
      "tags": [
        "rss",
        "auto-ingested"
      ]
    },
    {
      "id": "RSS-65247ba15f",
      "date": "2026-07-16",
      "region": "Middle East",
      "location": "Middle East",
      "lat": 29.0,
      "lon": 45.0,
      "category": "Geopolitical",
      "event_type": "Public news report",
      "source_name": "Al Jazeera",
      "source_url": "https://www.aljazeera.com/news/liveblog/2026/7/16/iran-war-live-us-carries-out-strikes-on-civilian-infrastructure-in-south?traffic_source=rss",
      "summary": "Iran war live: US carries out strikes on civilian infrastructure in south",
      "why_it_matters": "Auto-ingested from public RSS; pending analyst annotation.",
      "confidence": "Unverified",
      "risk_score": 6,
      "tags": [
        "rss",
        "auto-ingested"
      ]
    },
    {
      "id": "RSS-d3707d0fd3",
      "date": "2026-07-16",
      "region": "Global",
      "location": "Global",
      "lat": 10.0,
      "lon": 0.0,
      "category": "Geopolitical",
      "event_type": "Public news report",
      "source_name": "Al Jazeera",
      "source_url": "https://www.aljazeera.com/news/2026/7/16/palestinians-injured-in-israeli-settler-attacks-across-west-bank?traffic_source=rss",
      "summary": "Palestinians injured in Israeli settler attacks across West Bank",
      "why_it_matters": "Auto-ingested from public RSS; pending analyst annotation.",
      "confidence": "Unverified",
      "risk_score": 6,
      "tags": [
        "rss",
        "auto-ingested"
      ]
    },
    {
      "id": "RSS-a6562d7320",
      "date": "2026-07-16",
      "region": "Middle East",
      "location": "Middle East",
      "lat": 29.0,
      "lon": 45.0,
      "category": "Geopolitical",
      "event_type": "Public news report",
      "source_name": "Al Jazeera",
      "source_url": "https://www.aljazeera.com/news/2026/7/16/iran-condemns-barbaric-us-attack-near-childrens-cancer-hospital?traffic_source=rss",
      "summary": "Iran condemns \u2018barbaric\u2019 US attack near children\u2019s cancer hospital",
      "why_it_matters": "Auto-ingested from public RSS; pending analyst annotation.",
      "confidence": "Unverified",
      "risk_score": 6,
      "tags": [
        "rss",
        "auto-ingested"
      ]
    },
    {
      "id": "RSS-711d1de85c",
      "date": "2026-07-16",
      "region": "Europe / Russia-Ukraine",
      "location": "Europe / Russia-Ukraine",
      "lat": 49.0,
      "lon": 32.0,
      "category": "Military",
      "event_type": "Public news report",
      "source_name": "gCaptain (maritime)",
      "source_url": "https://gcaptain.com/ukraine-says-drone-campaign-has-hit-147-russian-linked-vessels-in-11-days/",
      "summary": "Ukraine Says Drone Campaign Has Hit 147 Russian-Linked Vessels in 11 Days",
      "why_it_matters": "Auto-ingested from public RSS; pending analyst annotation.",
      "confidence": "Unverified",
      "risk_score": 5,
      "tags": [
        "rss",
        "auto-ingested"
      ]
    },
    {
      "id": "RSS-73475c7db5",
      "date": "2026-07-16",
      "region": "Europe / Russia-Ukraine",
      "location": "Europe / Russia-Ukraine",
      "lat": 49.0,
      "lon": 32.0,
      "category": "Maritime",
      "event_type": "Public news report",
      "source_name": "gCaptain (maritime)",
      "source_url": "https://gcaptain.com/eus-next-russia-sanctions-package-adrift-following-greek-veto-to-protect-arctic-lng-shipping-interests/",
      "summary": "EU\u2019s Next Russia Sanctions Package Adrift Following Greek Veto to Protect Arctic LNG Shipping Interests",
      "why_it_matters": "Auto-ingested from public RSS; pending analyst annotation.",
      "confidence": "Unverified",
      "risk_score": 4,
      "tags": [
        "rss",
        "auto-ingested"
      ]
    },
    {
      "id": "RSS-a4ec26260b",
      "date": "2026-07-16",
      "region": "Europe / Russia-Ukraine",
      "location": "Europe / Russia-Ukraine",
      "lat": 49.0,
      "lon": 32.0,
      "category": "Geopolitical",
      "event_type": "Public news report",
      "source_name": "BBC World",
      "source_url": "https://www.bbc.co.uk/news/articles/cdx76069n3do?at_medium=RSS&at_campaign=rss",
      "summary": "Zelensky's removal of popular defence minister sparks protests in Ukraine",
      "why_it_matters": "Auto-ingested from public RSS; pending analyst annotation.",
      "confidence": "Unverified",
      "risk_score": 3,
      "tags": [
        "rss",
        "auto-ingested"
      ]
    },
    {
      "id": "RSS-a07a423486",
      "date": "2026-07-16",
      "region": "Europe / Russia-Ukraine",
      "location": "Europe / Russia-Ukraine",
      "lat": 49.0,
      "lon": 32.0,
      "category": "Geopolitical",
      "event_type": "Public news report",
      "source_name": "BBC World",
      "source_url": "https://www.bbc.co.uk/news/articles/cp305dx493do?at_medium=RSS&at_campaign=rss",
      "summary": "Teenager accused of carrying out sabotage actions in Poland for Russia",
      "why_it_matters": "Auto-ingested from public RSS; pending analyst annotation.",
      "confidence": "Unverified",
      "risk_score": 3,
      "tags": [
        "rss",
        "auto-ingested"
      ]
    },
    {
      "id": "RSS-416a93b883",
      "date": "2026-07-16",
      "region": "Global",
      "location": "Global",
      "lat": 10.0,
      "lon": 0.0,
      "category": "Geopolitical",
      "event_type": "Public news report",
      "source_name": "BBC World",
      "source_url": "https://www.bbc.co.uk/sport/football/articles/c75gnkl30vlo?at_medium=RSS&at_campaign=rss",
      "summary": "Fifa 'assessing match reports' over Falklands banner",
      "why_it_matters": "Auto-ingested from public RSS; pending analyst annotation.",
      "confidence": "Unverified",
      "risk_score": 3,
      "tags": [
        "rss",
        "auto-ingested"
      ]
    },
    {
      "id": "RSS-265812b145",
      "date": "2026-07-16",
      "region": "Global",
      "location": "Global",
      "lat": 10.0,
      "lon": 0.0,
      "category": "Geopolitical",
      "event_type": "Public news report",
      "source_name": "BBC World",
      "source_url": "https://www.bbc.co.uk/news/articles/cjrvdqyr5d5o?at_medium=RSS&at_campaign=rss",
      "summary": "White House teleprompter operator accused of making $100k off Trump speech bets",
      "why_it_matters": "Auto-ingested from public RSS; pending analyst annotation.",
      "confidence": "Unverified",
      "risk_score": 3,
      "tags": [
        "rss",
        "auto-ingested"
      ]
    },
    {
      "id": "RSS-64c1aa3790",
      "date": "2026-07-16",
      "region": "Global",
      "location": "Global",
      "lat": 10.0,
      "lon": 0.0,
      "category": "Geopolitical",
      "event_type": "Public news report",
      "source_name": "BBC World",
      "source_url": "https://www.bbc.co.uk/news/articles/c0m7n427xd8o?at_medium=RSS&at_campaign=rss",
      "summary": "Hundreds of Canada wildfires prompt US air quality alerts as smoke spreads south",
      "why_it_matters": "Auto-ingested from public RSS; pending analyst annotation.",
      "confidence": "Unverified",
      "risk_score": 3,
      "tags": [
        "rss",
        "auto-ingested"
      ]
    },
    {
      "id": "RSS-938c6a354c",
      "date": "2026-07-16",
      "region": "Middle East",
      "location": "Middle East",
      "lat": 29.0,
      "lon": 45.0,
      "category": "Geopolitical",
      "event_type": "Public news report",
      "source_name": "BBC World",
      "source_url": "https://www.bbc.co.uk/news/articles/c1m107yj327o?at_medium=RSS&at_campaign=rss",
      "summary": "JD Vance accuses Israel of 'manipulating' US public opinion to prolong Iran war",
      "why_it_matters": "Auto-ingested from public RSS; pending analyst annotation.",
      "confidence": "Unverified",
      "risk_score": 3,
      "tags": [
        "rss",
        "auto-ingested"
      ]
    },
    {
      "id": "RSS-b9d2dac9c8",
      "date": "2026-07-16",
      "region": "Global",
      "location": "Global",
      "lat": 10.0,
      "lon": 0.0,
      "category": "Geopolitical",
      "event_type": "Public news report",
      "source_name": "BBC World",
      "source_url": "https://www.bbc.co.uk/news/articles/c70g35n4518o?at_medium=RSS&at_campaign=rss",
      "summary": "Kris Jenner's mother Mary Jo dies aged 91",
      "why_it_matters": "Auto-ingested from public RSS; pending analyst annotation.",
      "confidence": "Unverified",
      "risk_score": 3,
      "tags": [
        "rss",
        "auto-ingested"
      ]
    },
    {
      "id": "RSS-f1d27f1a1f",
      "date": "2026-07-16",
      "region": "Global",
      "location": "Global",
      "lat": 10.0,
      "lon": 0.0,
      "category": "Geopolitical",
      "event_type": "Public news report",
      "source_name": "BBC World",
      "source_url": "https://www.bbc.co.uk/news/articles/c3v0xe5elzyo?at_medium=RSS&at_campaign=rss",
      "summary": "At least one dead in Texas floods ravaging same area where campers died",
      "why_it_matters": "Auto-ingested from public RSS; pending analyst annotation.",
      "confidence": "Unverified",
      "risk_score": 3,
      "tags": [
        "rss",
        "auto-ingested"
      ]
    },
    {
      "id": "RSS-34f8c511ed",
      "date": "2026-07-16",
      "region": "Global",
      "location": "Global",
      "lat": 10.0,
      "lon": 0.0,
      "category": "Geopolitical",
      "event_type": "Public news report",
      "source_name": "BBC World",
      "source_url": "https://www.bbc.co.uk/news/articles/cx2myxjv172o?at_medium=RSS&at_campaign=rss",
      "summary": "'Moment of joy' as Uganda discharges last Ebola patient",
      "why_it_matters": "Auto-ingested from public RSS; pending analyst annotation.",
      "confidence": "Unverified",
      "risk_score": 3,
      "tags": [
        "rss",
        "auto-ingested"
      ]
    },
    {
      "id": "RSS-60f1e4d93e",
      "date": "2026-07-16",
      "region": "Global",
      "location": "Global",
      "lat": 10.0,
      "lon": 0.0,
      "category": "Geopolitical",
      "event_type": "Public news report",
      "source_name": "BBC World",
      "source_url": "https://www.bbc.co.uk/news/articles/ce97zd8yx1xo?at_medium=RSS&at_campaign=rss",
      "summary": "Volunteer firefighter suspected of starting devastating France forest fire",
      "why_it_matters": "Auto-ingested from public RSS; pending analyst annotation.",
      "confidence": "Unverified",
      "risk_score": 3,
      "tags": [
        "rss",
        "auto-ingested"
      ]
    },
    {
      "id": "RSS-7c14601495",
      "date": "2026-07-16",
      "region": "Global",
      "location": "Global",
      "lat": 10.0,
      "lon": 0.0,
      "category": "Geopolitical",
      "event_type": "Public news report",
      "source_name": "BBC World",
      "source_url": "https://www.bbc.co.uk/news/articles/cvgwd4nz344o?at_medium=RSS&at_campaign=rss",
      "summary": "Children among dead at Algeria foster care home blaze - president",
      "why_it_matters": "Auto-ingested from public RSS; pending analyst annotation.",
      "confidence": "Unverified",
      "risk_score": 3,
      "tags": [
        "rss",
        "auto-ingested"
      ]
    },
    {
      "id": "RSS-a56016257d",
      "date": "2026-07-16",
      "region": "Global",
      "location": "Global",
      "lat": 10.0,
      "lon": 0.0,
      "category": "Geopolitical",
      "event_type": "Public news report",
      "source_name": "BBC World",
      "source_url": "https://www.bbc.co.uk/news/articles/cn4n9q538z2o?at_medium=RSS&at_campaign=rss",
      "summary": "Fraud crackdown on Ghana ID cards makes digital checks compulsory - photocopies banned",
      "why_it_matters": "Auto-ingested from public RSS; pending analyst annotation.",
      "confidence": "Unverified",
      "risk_score": 3,
      "tags": [
        "rss",
        "auto-ingested"
      ]
    },
    {
      "id": "RSS-dbfe4ccde6",
      "date": "2026-07-16",
      "region": "Global",
      "location": "Global",
      "lat": 10.0,
      "lon": 0.0,
      "category": "Geopolitical",
      "event_type": "Public news report",
      "source_name": "BBC World",
      "source_url": "https://www.bbc.co.uk/news/articles/ckg8g5z83glo?at_medium=RSS&at_campaign=rss",
      "summary": "JD Vance says Welsh castle was 'coolest thing I've ever seen'",
      "why_it_matters": "Auto-ingested from public RSS; pending analyst annotation.",
      "confidence": "Unverified",
      "risk_score": 3,
      "tags": [
        "rss",
        "auto-ingested"
      ]
    },
    {
      "id": "RSS-49ade968a2",
      "date": "2026-07-16",
      "region": "Global",
      "location": "Global",
      "lat": 10.0,
      "lon": 0.0,
      "category": "Geopolitical",
      "event_type": "Public news report",
      "source_name": "BBC World",
      "source_url": "https://www.bbc.co.uk/news/articles/c62x8ldxr7eo?at_medium=RSS&at_campaign=rss",
      "summary": "Chip giant TSMC pledges another $100bn to expand US production",
      "why_it_matters": "Auto-ingested from public RSS; pending analyst annotation.",
      "confidence": "Unverified",
      "risk_score": 3,
      "tags": [
        "rss",
        "auto-ingested"
      ]
    },
    {
      "id": "RSS-9dd9d8acf1",
      "date": "2026-07-16",
      "region": "Global",
      "location": "Global",
      "lat": 10.0,
      "lon": 0.0,
      "category": "Geopolitical",
      "event_type": "Public news report",
      "source_name": "BBC World",
      "source_url": "https://www.bbc.co.uk/news/articles/cddj7e8v767o?at_medium=RSS&at_campaign=rss",
      "summary": "Actor Sam Neill died from pneumonia, agent confirms",
      "why_it_matters": "Auto-ingested from public RSS; pending analyst annotation.",
      "confidence": "Unverified",
      "risk_score": 3,
      "tags": [
        "rss",
        "auto-ingested"
      ]
    },
    {
      "id": "RSS-694fae923e",
      "date": "2026-07-16",
      "region": "Global",
      "location": "Global",
      "lat": 10.0,
      "lon": 0.0,
      "category": "Military",
      "event_type": "Public news report",
      "source_name": "BBC World",
      "source_url": "https://www.bbc.co.uk/news/articles/cn0nlx18rz0o?at_medium=RSS&at_campaign=rss",
      "summary": "US military to start screening for testosterone deficiency, Hegseth says",
      "why_it_matters": "Auto-ingested from public RSS; pending analyst annotation.",
      "confidence": "Unverified",
      "risk_score": 3,
      "tags": [
        "rss",
        "auto-ingested"
      ]
    },
    {
      "id": "RSS-90638fab92",
      "date": "2026-07-16",
      "region": "Global",
      "location": "Global",
      "lat": 10.0,
      "lon": 0.0,
      "category": "Geopolitical",
      "event_type": "Public news report",
      "source_name": "BBC World",
      "source_url": "https://www.bbc.co.uk/news/articles/c1k13zj914mo?at_medium=RSS&at_campaign=rss",
      "summary": "I thought we'd grow old together, says band leader whose girlfriend died in Thai bar inferno",
      "why_it_matters": "Auto-ingested from public RSS; pending analyst annotation.",
      "confidence": "Unverified",
      "risk_score": 3,
      "tags": [
        "rss",
        "auto-ingested"
      ]
    },
    {
      "id": "RSS-ca3be36cf3",
      "date": "2026-07-16",
      "region": "Global",
      "location": "Global",
      "lat": 10.0,
      "lon": 0.0,
      "category": "Geopolitical",
      "event_type": "Public news report",
      "source_name": "BBC World",
      "source_url": "https://www.bbc.co.uk/news/articles/c5ywdl9ne3yo?at_medium=RSS&at_campaign=rss",
      "summary": "What to know about the Canadian and US wildfires and their impact",
      "why_it_matters": "Auto-ingested from public RSS; pending analyst annotation.",
      "confidence": "Unverified",
      "risk_score": 3,
      "tags": [
        "rss",
        "auto-ingested"
      ]
    },
    {
      "id": "RSS-0be6c4412a",
      "date": "2026-07-16",
      "region": "Global",
      "location": "Global",
      "lat": 10.0,
      "lon": 0.0,
      "category": "Geopolitical",
      "event_type": "Public news report",
      "source_name": "BBC World",
      "source_url": "https://www.bbc.co.uk/sport/football/articles/c9w0j104rvgo?at_medium=RSS&at_campaign=rss",
      "summary": "'A true miracle of destiny' - Messi and Lamine Yamal's incredible first meeting",
      "why_it_matters": "Auto-ingested from public RSS; pending analyst annotation.",
      "confidence": "Unverified",
      "risk_score": 3,
      "tags": [
        "rss",
        "auto-ingested"
      ]
    },
    {
      "id": "RSS-824ad580b8",
      "date": "2026-07-16",
      "region": "Global",
      "location": "Global",
      "lat": 10.0,
      "lon": 0.0,
      "category": "Geopolitical",
      "event_type": "Public news report",
      "source_name": "Al Jazeera",
      "source_url": "https://www.aljazeera.com/news/2026/7/16/venezuela-earthquake-number-of-known-dead-rises-to-nearly-5000-victims?traffic_source=rss",
      "summary": "Venezuela earthquake: Number of known dead rises to nearly 5,000 victims",
      "why_it_matters": "Auto-ingested from public RSS; pending analyst annotation.",
      "confidence": "Unverified",
      "risk_score": 3,
      "tags": [
        "rss",
        "auto-ingested"
      ]
    },
    {
      "id": "RSS-8d076b0993",
      "date": "2026-07-16",
      "region": "Middle East",
      "location": "Middle East",
      "lat": 29.0,
      "lon": 45.0,
      "category": "Geopolitical",
      "event_type": "Public news report",
      "source_name": "Al Jazeera",
      "source_url": "https://www.aljazeera.com/news/2026/7/16/vietnamese-activist-places-rare-national-spotlight-on-gazas-suffering?traffic_source=rss",
      "summary": "Vietnamese activist Bao Ngoc places rare national spotlight on Gaza",
      "why_it_matters": "Auto-ingested from public RSS; pending analyst annotation.",
      "confidence": "Unverified",
      "risk_score": 3,
      "tags": [
        "rss",
        "auto-ingested"
      ]
    },
    {
      "id": "RSS-5e697f12a1",
      "date": "2026-07-16",
      "region": "Middle East",
      "location": "Middle East",
      "lat": 29.0,
      "lon": 45.0,
      "category": "Military",
      "event_type": "Public news report",
      "source_name": "Al Jazeera",
      "source_url": "https://www.aljazeera.com/video/newsfeed/2026/7/16/qatar-rejects-israeli-reports-of-military-action-against-iran?traffic_source=rss",
      "summary": "Qatar rejects Israeli reports of military action against Iran",
      "why_it_matters": "Auto-ingested from public RSS; pending analyst annotation.",
      "confidence": "Unverified",
      "risk_score": 3,
      "tags": [
        "rss",
        "auto-ingested"
      ]
    },
    {
      "id": "RSS-a5fcc49de4",
      "date": "2026-07-16",
      "region": "Global",
      "location": "Global",
      "lat": 10.0,
      "lon": 0.0,
      "category": "Geopolitical",
      "event_type": "Public news report",
      "source_name": "Al Jazeera",
      "source_url": "https://www.aljazeera.com/news/2026/7/16/sadiq-khan-joins-house-of-lords-as-outgoing-uk-pm-names-26-new-peers?traffic_source=rss",
      "summary": "Sadiq Khan joins House of Lords as outgoing UK PM names 26 new peers",
      "why_it_matters": "Auto-ingested from public RSS; pending analyst annotation.",
      "confidence": "Unverified",
      "risk_score": 3,
      "tags": [
        "rss",
        "auto-ingested"
      ]
    },
    {
      "id": "RSS-5aa071b693",
      "date": "2026-07-16",
      "region": "Global",
      "location": "Global",
      "lat": 10.0,
      "lon": 0.0,
      "category": "Geopolitical",
      "event_type": "Public news report",
      "source_name": "Al Jazeera",
      "source_url": "https://www.aljazeera.com/video/newsfeed/2026/7/16/former-italian-motorway-chief-sentenced-over-bridge-collapse?traffic_source=rss",
      "summary": "Former Italian motorway chief sentenced over bridge collapse",
      "why_it_matters": "Auto-ingested from public RSS; pending analyst annotation.",
      "confidence": "Unverified",
      "risk_score": 3,
      "tags": [
        "rss",
        "auto-ingested"
      ]
    },
    {
      "id": "RSS-fe20ffb434",
      "date": "2026-07-16",
      "region": "Global",
      "location": "Global",
      "lat": 10.0,
      "lon": 0.0,
      "category": "Geopolitical",
      "event_type": "Public news report",
      "source_name": "Al Jazeera",
      "source_url": "https://www.aljazeera.com/news/2026/7/16/ilhan-omar-renews-push-for-us-to-join-icc-amid-trump-pressure?traffic_source=rss",
      "summary": "Ilhan Omar renews push for US to join ICC amid Trump pressure",
      "why_it_matters": "Auto-ingested from public RSS; pending analyst annotation.",
      "confidence": "Unverified",
      "risk_score": 3,
      "tags": [
        "rss",
        "auto-ingested"
      ]
    },
    {
      "id": "RSS-7c2c2ddf6c",
      "date": "2026-07-16",
      "region": "Global",
      "location": "Global",
      "lat": 10.0,
      "lon": 0.0,
      "category": "Geopolitical",
      "event_type": "Public news report",
      "source_name": "Al Jazeera",
      "source_url": "https://www.aljazeera.com/video/newsfeed/2026/7/16/grand-mosque-of-paris-celebrates-100-year-anniversary?traffic_source=rss",
      "summary": "Grand Mosque of Paris celebrates 100-year anniversary",
      "why_it_matters": "Auto-ingested from public RSS; pending analyst annotation.",
      "confidence": "Unverified",
      "risk_score": 3,
      "tags": [
        "rss",
        "auto-ingested"
      ]
    },
    {
      "id": "RSS-338fafab9d",
      "date": "2026-07-16",
      "region": "Global",
      "location": "Global",
      "lat": 10.0,
      "lon": 0.0,
      "category": "Geopolitical",
      "event_type": "Public news report",
      "source_name": "Al Jazeera",
      "source_url": "https://www.aljazeera.com/sports/2026/7/16/fifa-to-probe-argentinas-falklands-banner-display-at-world-cup-semifinal?traffic_source=rss",
      "summary": "FIFA to probe Argentina\u2019s Falklands banner display at World Cup semifinal",
      "why_it_matters": "Auto-ingested from public RSS; pending analyst annotation.",
      "confidence": "Unverified",
      "risk_score": 3,
      "tags": [
        "rss",
        "auto-ingested"
      ]
    },
    {
      "id": "RSS-3d3a0100e3",
      "date": "2026-07-16",
      "region": "Indo-Pacific",
      "location": "Indo-Pacific",
      "lat": 18.0,
      "lon": 118.0,
      "category": "Geopolitical",
      "event_type": "Public news report",
      "source_name": "Al Jazeera",
      "source_url": "https://www.aljazeera.com/news/liveblog/2026/7/16/donald-trump-live-us-president-to-deliver-primetime-address-on-elections?traffic_source=rss",
      "summary": "Donald Trump live: US president accuses China of election interference",
      "why_it_matters": "Auto-ingested from public RSS; pending analyst annotation.",
      "confidence": "Unverified",
      "risk_score": 3,
      "tags": [
        "rss",
        "auto-ingested"
      ]
    },
    {
      "id": "RSS-e3f72c475f",
      "date": "2026-07-16",
      "region": "Middle East",
      "location": "Middle East",
      "lat": 29.0,
      "lon": 45.0,
      "category": "Geopolitical",
      "event_type": "Public news report",
      "source_name": "Al Jazeera",
      "source_url": "https://www.aljazeera.com/opinions/2026/7/16/the-hardest-party-to-manage-in-the-iran-talks-isnt-iran?traffic_source=rss",
      "summary": "The hardest party to manage in the Iran talks isn\u2019t Iran",
      "why_it_matters": "Auto-ingested from public RSS; pending analyst annotation.",
      "confidence": "Unverified",
      "risk_score": 3,
      "tags": [
        "rss",
        "auto-ingested"
      ]
    },
    {
      "id": "RSS-03449e6074",
      "date": "2026-07-16",
      "region": "Middle East",
      "location": "Middle East",
      "lat": 29.0,
      "lon": 45.0,
      "category": "Geopolitical",
      "event_type": "Public news report",
      "source_name": "Al Jazeera",
      "source_url": "https://www.aljazeera.com/video/newsfeed/2026/7/16/syria-says-it-foiled-hezbollah-weapons-shipment?traffic_source=rss",
      "summary": "Syria says it foiled Hezbollah weapons shipment",
      "why_it_matters": "Auto-ingested from public RSS; pending analyst annotation.",
      "confidence": "Unverified",
      "risk_score": 3,
      "tags": [
        "rss",
        "auto-ingested"
      ]
    },
    {
      "id": "RSS-3d680839c4",
      "date": "2026-07-16",
      "region": "Global",
      "location": "Global",
      "lat": 10.0,
      "lon": 0.0,
      "category": "Geopolitical",
      "event_type": "Public news report",
      "source_name": "Al Jazeera",
      "source_url": "https://www.aljazeera.com/video/newsfeed/2026/7/16/wildfire-smoke-blankets-world-cup-final-stadium-before-kickoff?traffic_source=rss",
      "summary": "Wildfire smoke blankets World Cup final stadium before kickoff",
      "why_it_matters": "Auto-ingested from public RSS; pending analyst annotation.",
      "confidence": "Unverified",
      "risk_score": 3,
      "tags": [
        "rss",
        "auto-ingested"
      ]
    },
    {
      "id": "RSS-c6cff67ab3",
      "date": "2026-07-16",
      "region": "Middle East",
      "location": "Middle East",
      "lat": 29.0,
      "lon": 45.0,
      "category": "Geopolitical",
      "event_type": "Public news report",
      "source_name": "Al Jazeera",
      "source_url": "https://www.aljazeera.com/video/newsfeed/2026/7/16/how-syria-is-redefining-ties-with-russia?traffic_source=rss",
      "summary": "How Syria is redefining ties with Russia",
      "why_it_matters": "Auto-ingested from public RSS; pending analyst annotation.",
      "confidence": "Unverified",
      "risk_score": 3,
      "tags": [
        "rss",
        "auto-ingested"
      ]
    },
    {
      "id": "RSS-3788e08ed3",
      "date": "2026-07-16",
      "region": "Middle East",
      "location": "Middle East",
      "lat": 29.0,
      "lon": 45.0,
      "category": "Geopolitical",
      "event_type": "Public news report",
      "source_name": "Al Jazeera",
      "source_url": "https://www.aljazeera.com/news/2026/7/16/syria-seizes-advanced-weapons-it-says-were-bound-for-lebanons-hezbollah?traffic_source=rss",
      "summary": "Syria seizes advanced weapons it says were bound for Lebanon\u2019s Hezbollah",
      "why_it_matters": "Auto-ingested from public RSS; pending analyst annotation.",
      "confidence": "Unverified",
      "risk_score": 3,
      "tags": [
        "rss",
        "auto-ingested"
      ]
    },
    {
      "id": "RSS-7b7096a0db",
      "date": "2026-07-16",
      "region": "Global",
      "location": "Global",
      "lat": 10.0,
      "lon": 0.0,
      "category": "Geopolitical",
      "event_type": "Public news report",
      "source_name": "Al Jazeera",
      "source_url": "https://www.aljazeera.com/news/2026/7/16/nicaragua-severs-diplomatic-ties-with-italy-over-1978-murder-case?traffic_source=rss",
      "summary": "Nicaragua severs diplomatic ties with Italy over 1978 murder case",
      "why_it_matters": "Auto-ingested from public RSS; pending analyst annotation.",
      "confidence": "Unverified",
      "risk_score": 3,
      "tags": [
        "rss",
        "auto-ingested"
      ]
    },
    {
      "id": "RSS-f0d92022ea",
      "date": "2026-07-16",
      "region": "Middle East",
      "location": "Middle East",
      "lat": 29.0,
      "lon": 45.0,
      "category": "Maritime",
      "event_type": "Public news report",
      "source_name": "Al Jazeera",
      "source_url": "https://www.aljazeera.com/video/inside-story/2026/7/16/how-serious-is-irans-threat-to-disrupt-shipping-in-the-red-sea?traffic_source=rss",
      "summary": "How serious is Iran\u2019s threat to disrupt shipping in the Red Sea?",
      "why_it_matters": "Auto-ingested from public RSS; pending analyst annotation.",
      "confidence": "Unverified",
      "risk_score": 3,
      "tags": [
        "rss",
        "auto-ingested"
      ]
    },
    {
      "id": "RSS-3ad7401548",
      "date": "2026-07-16",
      "region": "Middle East",
      "location": "Middle East",
      "lat": 29.0,
      "lon": 45.0,
      "category": "Energy",
      "event_type": "Public news report",
      "source_name": "Al Jazeera",
      "source_url": "https://www.aljazeera.com/video/newsfeed/2026/7/16/iraq-says-19m-found-in-hideouts-linked-to-ex-oil-minister?traffic_source=rss",
      "summary": "Iraq says $19M found in hideouts linked to ex-oil minister",
      "why_it_matters": "Auto-ingested from public RSS; pending analyst annotation.",
      "confidence": "Unverified",
      "risk_score": 3,
      "tags": [
        "rss",
        "auto-ingested"
      ]
    },
    {
      "id": "RSS-89f5bcd5bc",
      "date": "2026-07-16",
      "region": "Global",
      "location": "Global",
      "lat": 10.0,
      "lon": 0.0,
      "category": "Geopolitical",
      "event_type": "Public news report",
      "source_name": "Al Jazeera",
      "source_url": "https://www.aljazeera.com/news/2026/7/16/ebola-spreading-more-quickly-in-drc-while-uganda-is-close-to-being-virus-free?traffic_source=rss",
      "summary": "Ebola spreading more quickly in DRC, while Uganda is close to being virus-free",
      "why_it_matters": "Auto-ingested from public RSS; pending analyst annotation.",
      "confidence": "Unverified",
      "risk_score": 3,
      "tags": [
        "rss",
        "auto-ingested"
      ]
    },
    {
      "id": "RSS-cbe0d61089",
      "date": "2026-07-16",
      "region": "Middle East",
      "location": "Middle East",
      "lat": 29.0,
      "lon": 45.0,
      "category": "Geopolitical",
      "event_type": "Public news report",
      "source_name": "Al Jazeera",
      "source_url": "https://www.aljazeera.com/video/newsfeed/2026/7/16/what-could-a-us-ground-invasion-of-iran-look-like?traffic_source=rss",
      "summary": "What could a US ground invasion of Iran look like?",
      "why_it_matters": "Auto-ingested from public RSS; pending analyst annotation.",
      "confidence": "Unverified",
      "risk_score": 3,
      "tags": [
        "rss",
        "auto-ingested"
      ]
    },
    {
      "id": "RSS-23c3f5c6bb",
      "date": "2026-07-16",
      "region": "Global",
      "location": "Global",
      "lat": 10.0,
      "lon": 0.0,
      "category": "Maritime",
      "event_type": "Public news report",
      "source_name": "gCaptain (maritime)",
      "source_url": "https://gcaptain.com/trump-administration-advances-first-offshore-critical-minerals-lease-sale-under-new-marine-minerals-agency/",
      "summary": "Trump Administration Advances First Offshore Critical Minerals Lease Sale Under New Marine Minerals Agency",
      "why_it_matters": "Auto-ingested from public RSS; pending analyst annotation.",
      "confidence": "Unverified",
      "risk_score": 3,
      "tags": [
        "rss",
        "auto-ingested"
      ]
    },
    {
      "id": "RSS-c764f6a811",
      "date": "2026-07-16",
      "region": "Europe / Russia-Ukraine",
      "location": "Europe / Russia-Ukraine",
      "lat": 49.0,
      "lon": 32.0,
      "category": "Energy",
      "event_type": "Public news report",
      "source_name": "gCaptain (maritime)",
      "source_url": "https://gcaptain.com/ukraine-hit-two-large-russia-linked-oil-tankers-in-black-sea/",
      "summary": "Ukraine Hit Two Large Russia-Linked Oil Tankers in Black Sea",
      "why_it_matters": "Auto-ingested from public RSS; pending analyst annotation.",
      "confidence": "Unverified",
      "risk_score": 3,
      "tags": [
        "rss",
        "auto-ingested"
      ]
    },
    {
      "id": "RSS-5ac70a6599",
      "date": "2026-07-16",
      "region": "Middle East",
      "location": "Middle East",
      "lat": 29.0,
      "lon": 45.0,
      "category": "Maritime",
      "event_type": "Public news report",
      "source_name": "gCaptain (maritime)",
      "source_url": "https://gcaptain.com/iran-tells-houthis-to-close-red-sea-gateway-if-u-s-hits-power-network/",
      "summary": "Iran Tells Houthis to Close Red Sea Gateway if U.S. Hits Power Network",
      "why_it_matters": "Auto-ingested from public RSS; pending analyst annotation.",
      "confidence": "Unverified",
      "risk_score": 3,
      "tags": [
        "rss",
        "auto-ingested"
      ]
    },
    {
      "id": "RSS-c8175750d0",
      "date": "2026-07-16",
      "region": "Global",
      "location": "Global",
      "lat": 10.0,
      "lon": 0.0,
      "category": "Maritime",
      "event_type": "Public news report",
      "source_name": "gCaptain (maritime)",
      "source_url": "https://gcaptain.com/saronic-picks-brownsville-for-3-billion-port-alpha-autonomous-shipyard/",
      "summary": "Saronic Picks Brownsville for $3 Billion \u2018Port Alpha\u2019 Autonomous Shipyard",
      "why_it_matters": "Auto-ingested from public RSS; pending analyst annotation.",
      "confidence": "Unverified",
      "risk_score": 3,
      "tags": [
        "rss",
        "auto-ingested"
      ]
    },
    {
      "id": "RSS-d0dc8b6cf9",
      "date": "2026-07-16",
      "region": "Global",
      "location": "Global",
      "lat": 10.0,
      "lon": 0.0,
      "category": "Energy",
      "event_type": "Public news report",
      "source_name": "gCaptain (maritime)",
      "source_url": "https://gcaptain.com/sea-lng-says-lng-continues-to-lead-alternative-fuel-orders-as-biomethane-supply-expands/",
      "summary": "SEA-LNG Says LNG Continues to Lead Alternative Fuel Orders as Biomethane Supply Expands",
      "why_it_matters": "Auto-ingested from public RSS; pending analyst annotation.",
      "confidence": "Unverified",
      "risk_score": 3,
      "tags": [
        "rss",
        "auto-ingested"
      ]
    },
    {
      "id": "RSS-f1979598b3",
      "date": "2026-07-16",
      "region": "Middle East",
      "location": "Middle East",
      "lat": 29.0,
      "lon": 45.0,
      "category": "Maritime",
      "event_type": "Public news report",
      "source_name": "gCaptain (maritime)",
      "source_url": "https://gcaptain.com/iran-us-skirmishes-worsen-as-hormuz-shipping-traffic-dwindles/",
      "summary": "Iran-US Skirmishes Worsen as Hormuz Shipping Traffic Dwindles",
      "why_it_matters": "Auto-ingested from public RSS; pending analyst annotation.",
      "confidence": "Unverified",
      "risk_score": 3,
      "tags": [
        "rss",
        "auto-ingested"
      ]
    },
    {
      "id": "RSS-b7122d7e58",
      "date": "2026-07-16",
      "region": "Middle East",
      "location": "Middle East",
      "lat": 29.0,
      "lon": 45.0,
      "category": "Maritime",
      "event_type": "Public news report",
      "source_name": "gCaptain (maritime)",
      "source_url": "https://gcaptain.com/india-ask-its-seafarers-not-to-take-hormuz-voyages/",
      "summary": "India Ask Its Seafarers Not to Take Hormuz Voyages",
      "why_it_matters": "Auto-ingested from public RSS; pending analyst annotation.",
      "confidence": "Unverified",
      "risk_score": 3,
      "tags": [
        "rss",
        "auto-ingested"
      ]
    },
    {
      "id": "RSS-1fddfde769",
      "date": "2026-07-16",
      "region": "United States",
      "location": "United States",
      "lat": 38.0,
      "lon": -97.0,
      "category": "Military",
      "event_type": "Public news report",
      "source_name": "U.S. DoD Releases",
      "source_url": "https://www.war.gov/News/News-Stories/Article/Article/4547749/wyoming-air-guardsmen-activate-for-wildland-firefighting-in-western-us/",
      "summary": "Wyoming Air Guardsmen Activate for Wildland Firefighting in Western U.S.",
      "why_it_matters": "Auto-ingested from public RSS; pending analyst annotation.",
      "confidence": "Unverified",
      "risk_score": 3,
      "tags": [
        "rss",
        "auto-ingested"
      ]
    },
    {
      "id": "RSS-27e03d384a",
      "date": "2026-07-16",
      "region": "United States",
      "location": "United States",
      "lat": 38.0,
      "lon": -97.0,
      "category": "Military",
      "event_type": "Public news report",
      "source_name": "U.S. DoD Releases",
      "source_url": "https://www.war.gov/News/News-Stories/Article/Article/4547957/ai-powered-chatbot-helps-streamline-recruiting/",
      "summary": "AI-Powered Chatbot Helps Streamline Recruiting",
      "why_it_matters": "Auto-ingested from public RSS; pending analyst annotation.",
      "confidence": "Unverified",
      "risk_score": 3,
      "tags": [
        "rss",
        "auto-ingested"
      ]
    },
    {
      "id": "RSS-8d9bce374b",
      "date": "2026-07-16",
      "region": "United States",
      "location": "United States",
      "lat": 38.0,
      "lon": -97.0,
      "category": "Military",
      "event_type": "Public news report",
      "source_name": "U.S. DoD Releases",
      "source_url": "https://www.war.gov/News/News-Stories/Article/Article/4547265/dha-official-says-tricare-pharmacy-ensuring-essential-medication-delivery-world/",
      "summary": "DHA Official Says TRICARE Pharmacy Ensuring Essential Medication Delivery Worldwide",
      "why_it_matters": "Auto-ingested from public RSS; pending analyst annotation.",
      "confidence": "Unverified",
      "risk_score": 3,
      "tags": [
        "rss",
        "auto-ingested"
      ]
    },
    {
      "id": "RSS-09cba15276",
      "date": "2026-07-16",
      "region": "United States",
      "location": "United States",
      "lat": 38.0,
      "lon": -97.0,
      "category": "Military",
      "event_type": "Public news report",
      "source_name": "U.S. DoD Releases",
      "source_url": "https://www.war.gov/News/News-Stories/Article/Article/4546926/trump-announces-10b-investment-in-defense-industry/",
      "summary": "Trump Announces $10B Investment in Defense Industry",
      "why_it_matters": "Auto-ingested from public RSS; pending analyst annotation.",
      "confidence": "Unverified",
      "risk_score": 3,
      "tags": [
        "rss",
        "auto-ingested"
      ]
    },
    {
      "id": "RSS-739ff033c6",
      "date": "2026-07-16",
      "region": "United States",
      "location": "United States",
      "lat": 38.0,
      "lon": -97.0,
      "category": "Military",
      "event_type": "Public news report",
      "source_name": "U.S. DoD Releases",
      "source_url": "https://www.war.gov/News/News-Stories/Article/Article/4545548/hegseth-hosts-iraqi-prime-minister-at-pentagon/",
      "summary": "Hegseth Hosts Iraqi Prime Minister at Pentagon",
      "why_it_matters": "Auto-ingested from public RSS; pending analyst annotation.",
      "confidence": "Unverified",
      "risk_score": 3,
      "tags": [
        "rss",
        "auto-ingested"
      ]
    },
    {
      "id": "RSS-21c8effbc5",
      "date": "2026-07-15",
      "region": "Global",
      "location": "Global",
      "lat": 10.0,
      "lon": 0.0,
      "category": "Geopolitical",
      "event_type": "Public news report",
      "source_name": "BBC World",
      "source_url": "https://www.bbc.co.uk/news/articles/c15y5wgj4x8o?at_medium=RSS&at_campaign=rss",
      "summary": "New monkey species with orange lips found 'hiding' in DR Congo forest",
      "why_it_matters": "Auto-ingested from public RSS; pending analyst annotation.",
      "confidence": "Unverified",
      "risk_score": 3,
      "tags": [
        "rss",
        "auto-ingested"
      ]
    },
    {
      "id": "RSS-002936233a",
      "date": "2026-07-15",
      "region": "Indo-Pacific",
      "location": "Indo-Pacific",
      "lat": 18.0,
      "lon": 118.0,
      "category": "Geopolitical",
      "event_type": "Public news report",
      "source_name": "BBC World",
      "source_url": "https://www.bbc.co.uk/news/articles/cd959q11g54o?at_medium=RSS&at_campaign=rss",
      "summary": "More people around the world now favour China over the US, Pew study suggests",
      "why_it_matters": "Auto-ingested from public RSS; pending analyst annotation.",
      "confidence": "Unverified",
      "risk_score": 3,
      "tags": [
        "rss",
        "auto-ingested"
      ]
    },
    {
      "id": "RSS-6e7862feb3",
      "date": "2026-07-15",
      "region": "Global",
      "location": "Global",
      "lat": 10.0,
      "lon": 0.0,
      "category": "Maritime",
      "event_type": "Public news report",
      "source_name": "gCaptain (maritime)",
      "source_url": "https://gcaptain.com/los-angeles-and-long-beach-post-strong-june-as-retailers-frontload-imports/",
      "summary": "Los Angeles and Long Beach Post Strong June as Retailers Frontload Imports",
      "why_it_matters": "Auto-ingested from public RSS; pending analyst annotation.",
      "confidence": "Unverified",
      "risk_score": 3,
      "tags": [
        "rss",
        "auto-ingested"
      ]
    },
    {
      "id": "RSS-750d0c7e63",
      "date": "2026-07-15",
      "region": "Global",
      "location": "Global",
      "lat": 10.0,
      "lon": 0.0,
      "category": "Maritime",
      "event_type": "Public news report",
      "source_name": "gCaptain (maritime)",
      "source_url": "https://gcaptain.com/port-of-los-angeles-tops-1-million-teus-in-record-june/",
      "summary": "Port of Los Angeles Tops 1 Million TEUs in Record June",
      "why_it_matters": "Auto-ingested from public RSS; pending analyst annotation.",
      "confidence": "Unverified",
      "risk_score": 3,
      "tags": [
        "rss",
        "auto-ingested"
      ]
    },
    {
      "id": "RSS-4d456293bb",
      "date": "2026-07-15",
      "region": "Middle East",
      "location": "Middle East",
      "lat": 29.0,
      "lon": 45.0,
      "category": "Maritime",
      "event_type": "Public news report",
      "source_name": "gCaptain (maritime)",
      "source_url": "https://gcaptain.com/after-hormuz-heres-why-the-red-sea-is-now-the-worlds-most-vulnerable-shipping-route/",
      "summary": "After Hormuz, Here\u2019s Why the Red Sea Is Now the World\u2019s Most Vulnerable Shipping Route",
      "why_it_matters": "Auto-ingested from public RSS; pending analyst annotation.",
      "confidence": "Unverified",
      "risk_score": 3,
      "tags": [
        "rss",
        "auto-ingested"
      ]
    },
    {
      "id": "RSS-b0cbc7f22b",
      "date": "2026-07-15",
      "region": "United States",
      "location": "United States",
      "lat": 38.0,
      "lon": -97.0,
      "category": "Military",
      "event_type": "Public news report",
      "source_name": "U.S. DoD Releases",
      "source_url": "https://www.war.gov/News/News-Stories/Article/Article/4546192/us-forces-continue-providing-disaster-relief-assistance-in-venezuela/",
      "summary": "U.S. Forces Continue Providing Disaster Relief Assistance in Venezuela",
      "why_it_matters": "Auto-ingested from public RSS; pending analyst annotation.",
      "confidence": "Unverified",
      "risk_score": 3,
      "tags": [
        "rss",
        "auto-ingested"
      ]
    },
    {
      "id": "RSS-afcd56f7fb",
      "date": "2026-07-14",
      "region": "United States",
      "location": "United States",
      "lat": 38.0,
      "lon": -97.0,
      "category": "Military",
      "event_type": "Public news report",
      "source_name": "U.S. DoD Releases",
      "source_url": "https://www.war.gov/News/News-Stories/Article/Article/4545273/dha-partners-with-marines-to-refine-portable-tbi-assessment-technology-for-aust/",
      "summary": "DHA Partners With Marines to Refine Portable TBI Assessment Technology for Austere Battlefield",
      "why_it_matters": "Auto-ingested from public RSS; pending analyst annotation.",
      "confidence": "Unverified",
      "risk_score": 3,
      "tags": [
        "rss",
        "auto-ingested"
      ]
    },
    {
      "id": "RSS-ec15428187",
      "date": "2026-07-14",
      "region": "United States",
      "location": "United States",
      "lat": 38.0,
      "lon": -97.0,
      "category": "Maritime",
      "event_type": "Public news report",
      "source_name": "U.S. DoD Releases",
      "source_url": "https://www.war.gov/News/News-Stories/Article/Article/4545141/dc-national-guard-boosts-homeland-defense-with-first-maritime-security-vessel/",
      "summary": "D.C. National Guard Boosts Homeland Defense With First Maritime Security Vessel",
      "why_it_matters": "Auto-ingested from public RSS; pending analyst annotation.",
      "confidence": "Unverified",
      "risk_score": 3,
      "tags": [
        "rss",
        "auto-ingested"
      ]
    },
    {
      "id": "RSS-7c280c3fd5",
      "date": "2026-07-14",
      "region": "Europe / Russia-Ukraine",
      "location": "Europe / Russia-Ukraine",
      "lat": 49.0,
      "lon": 32.0,
      "category": "Military",
      "event_type": "Public news report",
      "source_name": "U.S. DoD Releases",
      "source_url": "https://www.war.gov/News/News-Stories/Article/Article/4544895/skyfall-simulation-nato-partners-rehearse-downed-aircraft-response/",
      "summary": "Skyfall Simulation: NATO Partners Rehearse Downed Aircraft Response",
      "why_it_matters": "Auto-ingested from public RSS; pending analyst annotation.",
      "confidence": "Unverified",
      "risk_score": 3,
      "tags": [
        "rss",
        "auto-ingested"
      ]
    },
    {
      "id": "RSS-bb65968254",
      "date": "2026-07-13",
      "region": "Middle East",
      "location": "Middle East",
      "lat": 29.0,
      "lon": 45.0,
      "category": "Military",
      "event_type": "Public news report",
      "source_name": "U.S. DoD Releases",
      "source_url": "https://www.war.gov/News/News-Stories/Article/Article/4541171/centcom-completes-another-wave-of-strikes-against-iran/",
      "summary": "Centcom Completes Another Wave of Strikes Against Iran",
      "why_it_matters": "Auto-ingested from public RSS; pending analyst annotation.",
      "confidence": "Unverified",
      "risk_score": 6,
      "tags": [
        "rss",
        "auto-ingested"
      ]
    },
    {
      "id": "RSS-0c09aa1462",
      "date": "2026-07-13",
      "region": "United States",
      "location": "United States",
      "lat": 38.0,
      "lon": -97.0,
      "category": "Military",
      "event_type": "Public news report",
      "source_name": "U.S. DoD Releases",
      "source_url": "https://www.war.gov/News/News-Stories/Article/Article/4542849/war-department-changes-cybersecurity-maturity-model-certification-requirements/",
      "summary": "War Department Changes Cybersecurity Maturity Model Certification Requirements",
      "why_it_matters": "Auto-ingested from public RSS; pending analyst annotation.",
      "confidence": "Unverified",
      "risk_score": 3,
      "tags": [
        "rss",
        "auto-ingested"
      ]
    },
    {
      "id": "RSS-8d6f4b0bcf",
      "date": "2026-07-13",
      "region": "United States",
      "location": "United States",
      "lat": 38.0,
      "lon": -97.0,
      "category": "Military",
      "event_type": "Public news report",
      "source_name": "U.S. DoD Releases",
      "source_url": "https://www.war.gov/News/News-Stories/Article/Article/4541542/reduction-expected-for-japan-cost-of-living-allowance-rates/",
      "summary": "Reduction Expected for Japan Cost-of-Living Allowance Rates",
      "why_it_matters": "Auto-ingested from public RSS; pending analyst annotation.",
      "confidence": "Unverified",
      "risk_score": 3,
      "tags": [
        "rss",
        "auto-ingested"
      ]
    },
    {
      "id": "RSS-fdb1e55b58",
      "date": "2026-07-13",
      "region": "United States",
      "location": "United States",
      "lat": 38.0,
      "lon": -97.0,
      "category": "Military",
      "event_type": "Public news report",
      "source_name": "U.S. DoD Releases",
      "source_url": "https://www.war.gov/News/News-Stories/Article/Article/4541480/uss-san-antonio-assumes-relief-mission-in-venezuela/",
      "summary": "USS San Antonio Assumes Relief Mission in Venezuela",
      "why_it_matters": "Auto-ingested from public RSS; pending analyst annotation.",
      "confidence": "Unverified",
      "risk_score": 3,
      "tags": [
        "rss",
        "auto-ingested"
      ]
    },
    {
      "id": "RSS-df2d20e962",
      "date": "2026-07-10",
      "region": "United States",
      "location": "United States",
      "lat": 38.0,
      "lon": -97.0,
      "category": "Military",
      "event_type": "Public news report",
      "source_name": "U.S. DoD Releases",
      "source_url": "https://www.war.gov/News/News-Stories/Article/Article/4540150/alaska-national-guard-rescues-4-people-in-2-days/",
      "summary": "Alaska National Guard Rescues 4 People in 2 Days",
      "why_it_matters": "Auto-ingested from public RSS; pending analyst annotation.",
      "confidence": "Unverified",
      "risk_score": 3,
      "tags": [
        "rss",
        "auto-ingested"
      ]
    }
  ]
}